missingtvshows-1.3.2.dist-info/licenses/LICENSE.rst
mtvs/__init__.py
mtvs/_types.py
mtvs/Kodi/__init__.py
mtvs/Kodi/missing_tvshows.py
mtvs/etc/logging.yaml
mtvs/etc/missingTVShows-completion.bash
mtvs/etc/tvshows.conf
mtvs/main/__init__.py
mtvs/main/__main__.py
mtvs/main/main.py
mtvs/main/mainImpl.py
mtvs/utils/__init__.py
mtvs/utils/utilities.py
missingtvshows-1.3.2.dist-info/METADATA
missingtvshows-1.3.2.dist-info/WHEEL
missingtvshows-1.3.2.dist-info/entry_points.txt
missingtvshows-1.3.2.dist-info/top_level.txt
missingtvshows-1.3.2.dist-info/RECORD
