Metadata-Version: 2.4
Name: missingTvShows
Version: 1.3.2
Summary: Manages Kodi TVShows
Author-email: Andreas Ruppen <andreas.ruppen@gmail.com>
Project-URL: Changelog, https://github.com/digsim/missingTvShows/blob/main/CHANGES.rst
Project-URL: Source, https://github.com/digsim/missingTvShows
Project-URL: Tracker, https://github.com/digsim/missingTvShows/issues
Classifier: Programming Language :: Python :: 3
Classifier: Operating System :: OS Independent
Classifier: Development Status :: 5 - Production/Stable
Classifier: Environment :: Console
Classifier: Intended Audience :: Developers
Classifier: Topic :: Utilities
Requires-Python: >=3.10
License-File: LICENSE.rst
Requires-Dist: colorama==0.4.6
Requires-Dist: mysqlclient==2.2.7
Requires-Dist: progressbar2==4.5.0
Requires-Dist: pyparsing==3.2.5
Requires-Dist: PyYAML==6.0.3
Requires-Dist: SQLAlchemy==2.0.44
Requires-Dist: SQLAlchemy-Utils==0.42.0
Requires-Dist: tvdb-v4-official==1.1.0
Provides-Extra: docs
Requires-Dist: Sphinx>=8.1.3; extra == "docs"
Requires-Dist: sphinx_rtd_theme; extra == "docs"
Provides-Extra: test
Requires-Dist: build; extra == "test"
Requires-Dist: check-manifest>=0.50; extra == "test"
Requires-Dist: flake8; extra == "test"
Requires-Dist: pytest; extra == "test"
Requires-Dist: build; extra == "test"
Requires-Dist: twine; extra == "test"
Requires-Dist: coverage; extra == "test"
Dynamic: license-file
